odoo10_addon_sale_merge_draft_invoice-10.0.1.0.0-py2.7-nspkg.pth
odoo/addons/sale_merge_draft_invoice/README.rst
odoo/addons/sale_merge_draft_invoice/__init__.py
odoo/addons/sale_merge_draft_invoice/__manifest__.py
odoo/addons/sale_merge_draft_invoice/model/__init__.py
odoo/addons/sale_merge_draft_invoice/model/res_company.py
odoo/addons/sale_merge_draft_invoice/model/sale_config_settings.py
odoo/addons/sale_merge_draft_invoice/model/sale_order.py
odoo/addons/sale_merge_draft_invoice/security/sale_merge_draft_invoice_security.xml
odoo/addons/sale_merge_draft_invoice/static/description/icon.png
odoo/addons/sale_merge_draft_invoice/tests/__init__.py
odoo/addons/sale_merge_draft_invoice/tests/test_sale_merge_draft_invoice.py
odoo/addons/sale_merge_draft_invoice/view/sale_config_settings_views.xml
odoo/addons/sale_merge_draft_invoice/wizard/__init__.py
odoo/addons/sale_merge_draft_invoice/wizard/sale_make_invoice_advance.py
odoo/addons/sale_merge_draft_invoice/wizard/sale_make_invoice_advance_views.xml
odoo10_addon_sale_merge_draft_invoice-10.0.1.0.0.dist-info/DESCRIPTION.rst
odoo10_addon_sale_merge_draft_invoice-10.0.1.0.0.dist-info/METADATA
odoo10_addon_sale_merge_draft_invoice-10.0.1.0.0.dist-info/RECORD
odoo10_addon_sale_merge_draft_invoice-10.0.1.0.0.dist-info/WHEEL
odoo10_addon_sale_merge_draft_invoice-10.0.1.0.0.dist-info/metadata.json
odoo10_addon_sale_merge_draft_invoice-10.0.1.0.0.dist-info/namespace_packages.txt
odoo10_addon_sale_merge_draft_invoice-10.0.1.0.0.dist-info/top_level.txt
